<?xml version="1.0"?>
<configuration>
  <burst_buffer>
    <capacity>1638.4</capacity>
    <max_wrt_thrpt>2.1</max_wrt_thrpt>
    <max_rd_thrpt>5.5</max_rd_thrpt>
    <wrt_lim_per_day>8192</wrt_lim_per_day>
  </burst_buffer>
  <pfs>
    <capacity>242309426315264</capacity>
    <memory_range>
      <id>0</id>
      <limit>0.03125</limit>
      <bandwidth>
        <limit>50</limit>
        <saturation_point>800</saturation_point>
      </bandwidth>
    </memory_range>
    <memory_range>
      <id>1</id>
      <limit>0.125</limit>
      <bandwidth>
        <limit>250</limit>
        <saturation_point>800</saturation_point>
      </bandwidth>
    </memory_range>
    <memory_range>
      <id>2</id>
      <limit>0.25</limit>
      <bandwidth>
        <limit>420</limit>
        <saturation_point>1000</saturation_point>
      </bandwidth>
    </memory_range>
    <memory_range>
      <id>3</id>
      <limit>1</limit>
      <bandwidth>
        <limit>620</limit>
        <saturation_point>600</saturation_point>
      </bandwidth>
    </memory_range>
    <memory_range>
      <id>4</id>
      <limit>4</limit>
      <bandwidth>
        <limit>830</limit>
        <saturation_point>600</saturation_point>
      </bandwidth>
    </memory_range>
    <memory_range>
      <id>5</id>
      <limit>16</limit>
      <bandwidth>
        <limit>1280</limit>
        <saturation_point>600</saturation_point>
      </bandwidth>
    </memory_range>
    <memory_range>
      <id>6</id>
      <limit>32</limit>
      <bandwidth>
        <limit>1260</limit>
        <saturation_point>1000</saturation_point>
      </bandwidth>
    </memory_range>
    <memory_range>
      <id>7</id>
      <limit>64</limit>
      <bandwidth>
        <limit>1400</limit>
        <saturation_point>1000</saturation_point>
      </bandwidth>
    </memory_range>
    <memory_range>
      <id>8</id>
      <limit>128</limit>
      <bandwidth>
        <limit>1450</limit>
        <saturation_point>1000</saturation_point>
      </bandwidth>
    </memory_range>
    <max_clients>4608</max_clients>
  </pfs>
  <sys_fail>
    <distr name="weibull" shape="0.688" scale="5.45" location="0.0"/>
    <nodes>4608</nodes>
  </sys_fail>
  <node_failures>
    <node_failure name="failure1">
      <id>1</id>
      <frequency>14</frequency>
      <meanleadtime>61.04</meanleadtime>
      <stddev>43.37</stddev>
      <startphrase>"Call_Trace"</startphrase>
      <endphrase>"EXTERNAL_MCE_TOOL"</endphrase>
    </node_failure>
    <node_failure name="failure5">
      <id>5</id>
      <frequency>27</frequency>
      <meanleadtime>178</meanleadtime>
      <stddev>184</stddev>
      <startphrase>"EXTERNAL_MCE_TOOL"</startphrase>
      <endphrase>"node_health:5.1"</endphrase>
    </node_failure>
    <node_failure name="failure6">
      <id>6</id>
      <frequency>18</frequency>
      <meanleadtime>109.6</meanleadtime>
      <stddev>216.28</stddev>
      <startphrase>"mce_notify_irq"</startphrase>
      <endphrase>"Call_Trace"</endphrase>
    </node_failure>
    <node_failure name="failure7">
      <id>7</id>
      <frequency>5</frequency>
      <meanleadtime>9.5</meanleadtime>
      <stddev>11.58</stddev>
      <startphrase>"LNet:_Quiesce_start"</startphrase>
      <endphrase>"Call_Trace"</endphrase>
    </node_failure>
    <node_failure name="failure8">
      <id>8</id>
      <frequency>11406</frequency>
      <meanleadtime>33.48</meanleadtime>
      <stddev>12.44</stddev>
      <startphrase>"[Firmware_Bug]"</startphrase>
      <endphrase>"DVS:_verify_filesystem:_file_system"</endphrase>
    </node_failure>
    <node_failure name="failure9">
      <id>9</id>
      <frequency>51</frequency>
      <meanleadtime>1.33</meanleadtime>
      <stddev>7.55</stddev>
      <startphrase>"DVS:_verify_filesystem"</startphrase>
      <endphrase>"krsip:_can't_acquire"</endphrase>
    </node_failure>
    <node_failure name="failure10">
      <id>10</id>
      <frequency>33</frequency>
      <meanleadtime>51.23</meanleadtime>
      <stddev>104.58</stddev>
      <startphrase>"mce_notify_irq"</startphrase>
      <endphrase>"[gsockets]_debug"</endphrase>
    </node_failure>
  </node_failures>
  <soft_failures>
    <soft_failure name="failure2">
      <id>2</id>
      <frequency>13</frequency>
      <meanleadtime>485.9</meanleadtime>
      <stddev>198.7</stddev>
      <startphrase>"ERROR:_Type:2;_Severity:80;_Class:3;_Subclass:D;_Operation:_2"</startphrase>
      <endphrase>"bpmcd_init"</endphrase>
    </soft_failure>
    <soft_failure name="failure3">
      <id>3</id>
      <frequency>8610</frequency>
      <meanleadtime>45.78</meanleadtime>
      <stddev>80.15</stddev>
      <startphrase>"LustreError:_27764:0:"</startphrase>
      <endphrase>"LNet:_27678:0:"</endphrase>
    </soft_failure>
    <soft_failure name="failure4">
      <id>4</id>
      <frequency>187</frequency>
      <meanleadtime>53.29</meanleadtime>
      <stddev>143.35</stddev>
      <startphrase>"krsip:_RSIP_server"</startphrase>
      <endphrase>"LNetError"</endphrase>
    </soft_failure>
  </soft_failures>
  <ckpt_placement>
    <updt_window>2</updt_window>
  </ckpt_placement>
  <apps>
    <app name="CHIMERA">
      <id>0</id>
      <start_time>0.0</start_time>
      <comp_period>1.9616</comp_period>
      <ckpt_size>163840.0</ckpt_size>
      <clients>2272</clients>
      <client_id_start>0</client_id_start>
      <client_id_end>2271</client_id_end>
      <total_comp_time>360</total_comp_time>
      <ckpt2bb_percnt>0.5228</ckpt2bb_percnt>
    </app>
    <app name="XGC">
      <id>2</id>
      <start_time>0.0</start_time>
      <comp_period>1.1650</comp_period>
      <ckpt_size>37926</ckpt_size>
      <clients>1515</clients>
      <client_id_start>2777</client_id_start>
      <client_id_end>4291</client_id_end>
      <total_comp_time>240</total_comp_time>
      <ckpt2bb_percnt>0.0</ckpt2bb_percnt>
    </app>
    <app name="S3D">
      <id>1</id>
      <start_time>0.0</start_time>
      <comp_period>1.7262</comp_period>
      <ckpt_size>5120.0</ckpt_size>
      <clients>505</clients>
      <client_id_start>2272</client_id_start>
      <client_id_end>2776</client_id_end>
      <total_comp_time>240</total_comp_time>
      <ckpt2bb_percnt>0.0009</ckpt2bb_percnt>
    </app>
    <app name="GYRO">
      <id>5</id>
      <start_time>0.0</start_time>
      <comp_period>0.6786</comp_period>
      <ckpt_size>50.0</ckpt_size>
      <clients>126</clients>
      <client_id_start>4482</client_id_start>
      <client_id_end>4607</client_id_end>
      <total_comp_time>120</total_comp_time>
      <ckpt2bb_percnt>0.0139</ckpt2bb_percnt>
    </app>
    <app name="POP">
      <id>3</id>
      <start_time>0.0</start_time>     
      <comp_period>0.4392</comp_period>
      <ckpt_size>26.0</ckpt_size>
      <clients>126</clients>
      <client_id_start>4292</client_id_start>
      <client_id_end>4417</client_id_end>
      <total_comp_time>480</total_comp_time>
      <ckpt2bb_percnt>0.2429</ckpt2bb_percnt>
    </app>
    <app name="VULCAN">
      <id>4</id>
      <start_time>0.0</start_time>
      <comp_period>0.0828</comp_period>
      <ckpt_size>0.83</ckpt_size>
      <clients>64</clients>
      <client_id_start>4418</client_id_start>
      <client_id_end>4481</client_id_end>
      <total_comp_time>720</total_comp_time>
      <ckpt2bb_percnt>0.9269</ckpt2bb_percnt>
    </app>
  </apps>
</configuration>
